{
  "version": "7",
  "dialect": "postgresql",
  "entries": [
    {
      "idx": 0,
      "version": "7",
      "when": 1772570186103,
      "tag": "0000_nostalgic_meteorite",
      "breakpoints": true
    },
    {
      "idx": 1,
      "version": "7",
      "when": 1778098949569,
      "tag": "0001_slippery_ogun",
      "breakpoints": true
    },
    {
      "idx": 2,
      "version": "7",
      "when": 1778188894852,
      "tag": "0002_lethal_mongu",
      "breakpoints": true
    },
    {
      "idx": 3,
      "version": "7",
      "when": 1778189121058,
      "tag": "0003_careless_enchantress",
      "breakpoints": true
    },
    {
      "idx": 4,
      "version": "7",
      "when": 1778189422589,
      "tag": "0004_familiar_slyde",
      "breakpoints": true
    },
    {
      "idx": 5,
      "version": "7",
      "when": 1778240419920,
      "tag": "0005_old_black_tom",
      "breakpoints": true
    },
    {
      "idx": 6,
      "version": "7",
      "when": 1778455179477,
      "tag": "0006_worthless_lila_cheney",
      "breakpoints": true
    },
    {
      "idx": 7,
      "version": "7",
      "when": 1778758493482,
      "tag": "0007_condemned_dark_phoenix",
      "breakpoints": true
    },
    {
      "idx": 8,
      "version": "7",
      "when": 1779060898490,
      "tag": "0008_natural_bushwacker",
      "breakpoints": true
    }
  ]
}